agentx/__init__.py
agentx/cli.py
agentx/utils.py
agentx/agents/__init__.py
agentx/agents/base_agent.py
agentx/agents/action/__init__.py
agentx/agents/action/action.py
agentx/agents/action/prompt.jinja2
agentx/agents/chat/__init__.py
agentx/agents/chat/chat.py
agentx/agents/chat/prompt.jinja2
agentx/agents/coder/__init__.py
agentx/agents/coder/coder.py
agentx/agents/coder/prompt.jinja2
agentx/data_reader/__init__.py
agentx/data_reader/loaders.py
agentx/engine/__init__.py
agentx/engine/configuration.py
agentx/engine/engine.py
agentx/engine_websocket/__init__.py
agentx/engine_websocket/client.py
agentx/engine_websocket/serve.py
agentx/llama_cpp/__init__.py
agentx/llama_cpp/_configuration.py
agentx/llama_cpp/_quantize.py
agentx/llama_cpp/_utils.py
agentx/llama_cpp/inference.py
agentx/prompt_templates/__init__.py
agentx/prompt_templates/prompt_template_chatml.jinja2
agentx/prompt_templates/prompt_template_gemma.jinja2
agentx/prompt_templates/prompt_template_llama.jinja2
agentx/prompt_templates/prompt_template_llama_3.jinja2
agentx/prompt_templates/prompt_template_open_chat.jinja2
agentx/prompt_templates/prompt_template_zephyr.jinja2
agentx/prompt_templates/prompt_templates.py
AgentX-0.0.27.dist-info/LICENSE
AgentX-0.0.27.dist-info/METADATA
AgentX-0.0.27.dist-info/WHEEL
AgentX-0.0.27.dist-info/entry_points.txt
AgentX-0.0.27.dist-info/top_level.txt
AgentX-0.0.27.dist-info/RECORD
