Metadata-Version: 2.1
Name: AgentX
Version: 0.0.27
Summary: AgentX: Seamlessly integrate intelligent agents into your projects. Empower your applications with advanced AI capabilities.
Author-email: Erfan Zare Chavoshi <erfanzare810@gmail.com>
License: MIT
Project-URL: Homepage, https://github.com/erfanzar/AgentX
Project-URL: Issues, https://github.com/erfanzar/AgentX/issues
Project-URL: Documentation, https://erfanzar.github.io/AgentX
Classifier: Programming Language :: Python :: 3
Classifier: Programming Language :: Python :: 3.8
Classifier: Programming Language :: Python :: 3.9
Classifier: Programming Language :: Python :: 3.10
Classifier: Programming Language :: Python :: 3.11
Classifier: Programming Language :: Python :: 3.12
Requires-Python: >=3.8
License-File: LICENSE
Requires-Dist: typing ~=3.7.4.3
Requires-Dist: ipython ~=8.17.2
Requires-Dist: tqdm ~=4.64.1
Requires-Dist: pydantic ==2.5.3
Requires-Dist: setuptools ~=68.1.2
Requires-Dist: gradio ~=4.18.0
Requires-Dist: numpy ~=1.26.2
Requires-Dist: uvicorn ~=0.23.2
Requires-Dist: pydantic-core ==2.14.6
Requires-Dist: requests ~=2.31.0
Requires-Dist: transformers >=4.36.1
Requires-Dist: huggingface-hub >=0.20.1
Requires-Dist: absl-py ==2.0.0
Requires-Dist: Jinja2 ~=3.1.2
Requires-Dist: websocket-client
Provides-Extra: all
Requires-Dist: AgentX[gguf,ollama,rag,torch] ; extra == 'all'
Provides-Extra: gguf
Requires-Dist: llama-cpp-python ; extra == 'gguf'
Provides-Extra: ollama
Requires-Dist: ollama ; extra == 'ollama'
Provides-Extra: rag
Requires-Dist: faiss-cpu ; extra == 'rag'
Requires-Dist: sentence-transformers ; extra == 'rag'
Requires-Dist: pymupdf ; extra == 'rag'
Requires-Dist: python-docx ; extra == 'rag'
Provides-Extra: torch
Requires-Dist: torch ; extra == 'torch'
Requires-Dist: bitsandbytes ; extra == 'torch'
Requires-Dist: accelerate ; extra == 'torch'
